package_Kolekar/Ensemble_Learning/Avg_Ensemble.py
package_Kolekar/Gradient_Descent/ElasticNetRegression.py
package_Kolekar/Gradient_Descent/LassoRegression.py
package_Kolekar/Gradient_Descent/LinearRegression.py
package_Kolekar/Gradient_Descent/RidgeRegression.py
package_Kolekar-0.5.dist-info/LICENCE
package_Kolekar-0.5.dist-info/METADATA
package_Kolekar-0.5.dist-info/WHEEL
package_Kolekar-0.5.dist-info/top_level.txt
package_Kolekar-0.5.dist-info/RECORD
