Metadata-Version: 2.1
Name: package-Kolekar
Version: 0.5
Summary: UNKNOWN
Home-page: UNKNOWN
Author: Tushar_Kolekar
Author-email: tusharkolekar24@gmail.com
License: MIT
Platform: UNKNOWN
Classifier: License :: OSI Approved :: MIT License
Classifier: Operating System :: OS Independent
Classifier: Programming Language :: Python :: 3.6
License-File: LICENCE
Requires-Dist: numpy
Requires-Dist: sklearn
Requires-Dist: pandas
